haystack_experimental/__init__.py
haystack_experimental/chat_message_stores/__init__.py
haystack_experimental/chat_message_stores/in_memory.py
haystack_experimental/chat_message_stores/types.py
haystack_experimental/components/__init__.py
haystack_experimental/components/agents/__init__.py
haystack_experimental/components/agents/agent.py
haystack_experimental/components/agents/human_in_the_loop/__init__.py
haystack_experimental/components/agents/human_in_the_loop/breakpoint.py
haystack_experimental/components/agents/human_in_the_loop/dataclasses.py
haystack_experimental/components/agents/human_in_the_loop/errors.py
haystack_experimental/components/agents/human_in_the_loop/policies.py
haystack_experimental/components/agents/human_in_the_loop/strategies.py
haystack_experimental/components/agents/human_in_the_loop/types.py
haystack_experimental/components/agents/human_in_the_loop/user_interfaces.py
haystack_experimental/components/embedders/__init__.py
haystack_experimental/components/embedders/types/__init__.py
haystack_experimental/components/embedders/types/protocol.py
haystack_experimental/components/generators/__init__.py
haystack_experimental/components/generators/chat/__init__.py
haystack_experimental/components/generators/chat/openai.py
haystack_experimental/components/preprocessors/__init__.py
haystack_experimental/components/preprocessors/embedding_based_document_splitter.py
haystack_experimental/components/preprocessors/md_header_level_inferrer.py
haystack_experimental/components/retrievers/__init__.py
haystack_experimental/components/retrievers/chat_message_retriever.py
haystack_experimental/components/retrievers/types/__init__.py
haystack_experimental/components/retrievers/types/protocol.py
haystack_experimental/components/summarizers/__init__.py
haystack_experimental/components/summarizers/llm_summarizer.py
haystack_experimental/components/writers/__init__.py
haystack_experimental/components/writers/chat_message_writer.py
haystack_experimental-0.15.1.dist-info/METADATA
haystack_experimental-0.15.1.dist-info/WHEEL
haystack_experimental-0.15.1.dist-info/licenses/LICENSE
haystack_experimental-0.15.1.dist-info/licenses/LICENSE-MIT.txt
haystack_experimental-0.15.1.dist-info/RECORD
